smime/__init__.py
smime/block.py
smime/cert.py
smime/encrypt.py
smime/encrypt_test.py
smime/print_util.py
smime/print_util_test.py
smime/pubkey.py
smime/test/__init__.py
smime/test/test_config.py
smime/test/time_utils.py
smime/tools/__init__.py
smime/tools/cert_util.py
smime/tools/cms_util.py
smime-0.0.5.dist-info/AUTHORS
smime-0.0.5.dist-info/LICENSE
smime-0.0.5.dist-info/METADATA
smime-0.0.5.dist-info/WHEEL
smime-0.0.5.dist-info/top_level.txt
smime-0.0.5.dist-info/RECORD
